config/ODataToSTAC_template.json
config/cadip_search_config.yaml
config/cadip_session_ODataToSTAC_template.json
config/cadip_sessions_stac_mapper.json
config/cadip_stac_mapper.json
config/cadip_ws_config.yaml
config/cadip_ws_config_token_module.yaml
rs_server_cadip/__init__.py
rs_server_cadip/api/__init__.py
rs_server_cadip/api/cadip_download.py
rs_server_cadip/api/cadip_search.py
rs_server_cadip/api/cadip_status.py
rs_server_cadip/cadip_download_status.py
rs_server_cadip/cadip_retriever.py
rs_server_cadip/cadip_utils.py
rs_server_cadip/fastapi/__init__.py
rs_server_cadip/fastapi/cadip_app.py
rs_server_cadip/fastapi/cadip_routers.py
rs_server_cadip-99.99.dist-info/METADATA
rs_server_cadip-99.99.dist-info/WHEEL
rs_server_cadip-99.99.dist-info/RECORD
