Metadata-Version: 2.1
Name: rs-server-cadip
Version: 99.99
Summary: Copernicus Sentinel rs-server, CADIP service.
Home-page: https://home.rs-python.eu/
License: Apache-2.0
Keywords: stac,copernicus,sentinel,processing,cadip
Author: ESA under contract with Airbus and CS
Author-email: ops_coprs@airbus.com
Requires-Python: ==3.11.7
Classifier: Development Status :: 3 - Alpha
Classifier: Framework :: FastAPI
Classifier: Framework :: OpenTelemetry
Classifier: Intended Audience :: Developers
Classifier: Intended Audience :: Science/Research
Classifier: License :: OSI Approved :: Apache Software License
Classifier: Programming Language :: Python :: 3
Classifier: Programming Language :: Python :: 3.11
Classifier: Topic :: Scientific/Engineering :: GIS
Classifier: Topic :: Scientific/Engineering :: Image Processing
Requires-Dist: rs-server-common
Project-URL: Documentation, https://home.rs-python.eu/rs-documentation/rs-server/docs/doc/users/functionalities/#cadip
Project-URL: Repository, https://github.com/RS-PYTHON/rs-server
